LICENSE
MANIFEST.in
README.md
setup.cfg
setup.py
depscan/__init__.py
depscan/cli.py
depscan/lib/__init__.py
depscan/lib/analysis.py
depscan/lib/audit.py
depscan/lib/bom.py
depscan/lib/config.py
depscan/lib/license.py
depscan/lib/logger.py
depscan/lib/normalize.py
depscan/lib/pkg_query.py
depscan/lib/utils.py
h2_depscan.egg-info/PKG-INFO
h2_depscan.egg-info/SOURCES.txt
h2_depscan.egg-info/dependency_links.txt
h2_depscan.egg-info/entry_points.txt
h2_depscan.egg-info/requires.txt
h2_depscan.egg-info/top_level.txt
test/test_analysis.py
test/test_bom.py
test/test_license.py
test/test_norm.py
test/test_pkg_query.py
test/test_utils.py
vendor/__init__.py
vendor/choosealicense.com/_data/fields.yml
vendor/choosealicense.com/_data/meta.yml
vendor/choosealicense.com/_data/rules.yml
vendor/choosealicense.com/_licenses/0bsd.txt
vendor/choosealicense.com/_licenses/afl-3.0.txt
vendor/choosealicense.com/_licenses/agpl-3.0.txt
vendor/choosealicense.com/_licenses/apache-2.0.txt
vendor/choosealicense.com/_licenses/artistic-2.0.txt
vendor/choosealicense.com/_licenses/bsd-2-clause.txt
vendor/choosealicense.com/_licenses/bsd-3-clause-clear.txt
vendor/choosealicense.com/_licenses/bsd-3-clause.txt
vendor/choosealicense.com/_licenses/bsd-4-clause.txt
vendor/choosealicense.com/_licenses/bsl-1.0.txt
vendor/choosealicense.com/_licenses/cc-by-4.0.txt
vendor/choosealicense.com/_licenses/cc-by-sa-4.0.txt
vendor/choosealicense.com/_licenses/cc0-1.0.txt
vendor/choosealicense.com/_licenses/cecill-2.1.txt
vendor/choosealicense.com/_licenses/ecl-2.0.txt
vendor/choosealicense.com/_licenses/epl-1.0.txt
vendor/choosealicense.com/_licenses/epl-2.0.txt
vendor/choosealicense.com/_licenses/eupl-1.1.txt
vendor/choosealicense.com/_licenses/eupl-1.2.txt
vendor/choosealicense.com/_licenses/gpl-2.0.txt
vendor/choosealicense.com/_licenses/gpl-3.0.txt
vendor/choosealicense.com/_licenses/isc.txt
vendor/choosealicense.com/_licenses/lgpl-2.1.txt
vendor/choosealicense.com/_licenses/lgpl-3.0.txt
vendor/choosealicense.com/_licenses/lppl-1.3c.txt
vendor/choosealicense.com/_licenses/mit-0.txt
vendor/choosealicense.com/_licenses/mit.txt
vendor/choosealicense.com/_licenses/mpl-2.0.txt
