Metadata-Version: 2.1
Name: h2-depscan
Version: 2.2.1
Summary: Security assessment for project dependencies that is entirely open-source and based on known vulnerabilities and advisories.
Home-page: https://gitlab.com/hhammoudi/h2-depscan
Author: h2 security
Author-email: blue-team@h2security.io
License: UNKNOWN
Platform: UNKNOWN
Classifier: Development Status :: 5 - Production/Stable
Classifier: Intended Audience :: Developers
Classifier: Intended Audience :: System Administrators
Classifier: Topic :: Utilities
Classifier: Topic :: Security
Classifier: Programming Language :: Python :: 3.8
Classifier: Programming Language :: Python :: 3.9
Classifier: License :: OSI Approved :: MIT License
Classifier: Operating System :: OS Independent
Requires-Python: >=3.8
